markline/__init__.py
markline-0.3.3.dist-info/LICENSE.md
markline-0.3.3.dist-info/METADATA
markline-0.3.3.dist-info/WHEEL
markline-0.3.3.dist-info/RECORD
