Metadata-Version: 2.1
Name: markline
Version: 0.3.3
Summary: Convert Markup to Markdown with a transformation pipeline.
Home-page: https://github.com/hughcameron/markline
License: MIT
Author: Hugh Cameron
Author-email: hescameron+githubprojects@gmail.com
Requires-Python: >=3.10.6,<4.0.0
Classifier: License :: OSI Approved :: MIT License
Classifier: Programming Language :: Python :: 3
Classifier: Programming Language :: Python :: 3.11
Classifier: Programming Language :: Python :: 3.12
Requires-Dist: beautifulsoup4 (>=4.12.2,<5.0.0)
Requires-Dist: furl (>=2.1.3,<3.0.0)
Requires-Dist: httpx (>=0.24.1,<0.25.0)
Requires-Dist: pypandoc (>=1.11,<2.0)
Project-URL: Repository, https://github.com/hughcameron/markline
